koia/__init__.py
koia/builders/__init__.py
koia/builders/fetch_builder.py
koia/builders/query_builder.py
koia/builders/utils.py
koia/database/__init__.py
koia/database/connector.py
koia/models/__init__.py
koia/models/model.py
koia/types/__init__.py
koia/types/generic_types.py
koia/types/model_types.py
tests/__init__.py
tests/conftest.py
tests/test_connector.py
koia-0.0.12.dist-info/METADATA
koia-0.0.12.dist-info/WHEEL
koia-0.0.12.dist-info/top_level.txt
koia-0.0.12.dist-info/RECORD
