Metadata-Version: 2.1
Name: koia
Version: 0.0.12
Summary: Sql query builder interface
Home-page: https://github.com/Kel0/koia
Author: Kel0
Author-email: rickeyfsimple@gmail.com
License: UNKNOWN
Platform: UNKNOWN
Classifier: Programming Language :: Python :: 3
Classifier: Operating System :: OS Independent
Requires-Python: >=3.7
